Metadata-Version: 2.1
Name: disstat
Version: 1.0.1
Summary: A Python wrapper for the DisStat API.
Home-page: https://github.com/TheUntraceable/disstat
Author: Your Name
Author-email: TheUntraceable@The-Untraceable.xz
Classifier: Development Status :: 5 - Production/Stable
Classifier: Intended Audience :: Developers
Classifier: License :: OSI Approved :: MIT License
Classifier: Programming Language :: Python :: 3
Classifier: Programming Language :: Python :: 3.6
Classifier: Programming Language :: Python :: 3.7
Classifier: Programming Language :: Python :: 3.8
